ZetcodePyqt4Jiaocheng/README.md
ZetcodePyqt4Jiaocheng/__init__.py
ZetcodePyqt4Jiaocheng/__main__.py
ZetcodePyqt4Jiaocheng/file.epub
ZetcodePyqt4Jiaocheng/index.html
ZetcodePyqt4Jiaocheng/css/__init__.py
ZetcodePyqt4Jiaocheng/css/annotations.css
ZetcodePyqt4Jiaocheng/css/main.css
ZetcodePyqt4Jiaocheng/css/normalize.css
ZetcodePyqt4Jiaocheng/css/popup.css
ZetcodePyqt4Jiaocheng/font/__init__.py
ZetcodePyqt4Jiaocheng/font/fontello.eot
ZetcodePyqt4Jiaocheng/font/fontello.svg
ZetcodePyqt4Jiaocheng/font/fontello.ttf
ZetcodePyqt4Jiaocheng/font/fontello.woff
ZetcodePyqt4Jiaocheng/img/__init__.py
ZetcodePyqt4Jiaocheng/img/annotator-glyph-sprite.png
ZetcodePyqt4Jiaocheng/img/annotator-icon-sprite.png
ZetcodePyqt4Jiaocheng/img/apple-touch-icon.png
ZetcodePyqt4Jiaocheng/img/cancelfullscreen.png
ZetcodePyqt4Jiaocheng/img/close.png
ZetcodePyqt4Jiaocheng/img/fullscreen.png
ZetcodePyqt4Jiaocheng/img/loader.gif
ZetcodePyqt4Jiaocheng/img/menu-icon.png
ZetcodePyqt4Jiaocheng/img/save.png
ZetcodePyqt4Jiaocheng/img/saved.png
ZetcodePyqt4Jiaocheng/img/settings-s.png
ZetcodePyqt4Jiaocheng/img/settings.png
ZetcodePyqt4Jiaocheng/img/star.png
ZetcodePyqt4Jiaocheng/js/__init__.py
ZetcodePyqt4Jiaocheng/js/epub.js
ZetcodePyqt4Jiaocheng/js/epub.min.js
ZetcodePyqt4Jiaocheng/js/epub.min.map
ZetcodePyqt4Jiaocheng/js/hooks.min.js
ZetcodePyqt4Jiaocheng/js/hooks.min.map
ZetcodePyqt4Jiaocheng/js/reader.js
ZetcodePyqt4Jiaocheng/js/reader.js.map
ZetcodePyqt4Jiaocheng/js/reader.min.js
ZetcodePyqt4Jiaocheng/js/reader.min.map
ZetcodePyqt4Jiaocheng/js/hooks/__init__.py
ZetcodePyqt4Jiaocheng/js/hooks/extensions/__init__.py
ZetcodePyqt4Jiaocheng/js/hooks/extensions/highlight.js
ZetcodePyqt4Jiaocheng/js/libs/__init__.py
ZetcodePyqt4Jiaocheng/js/libs/jquery.min.js
ZetcodePyqt4Jiaocheng/js/libs/localforage.min.js
ZetcodePyqt4Jiaocheng/js/libs/screenfull.js
ZetcodePyqt4Jiaocheng/js/libs/screenfull.min.js
ZetcodePyqt4Jiaocheng/js/libs/zip.min.js
ZetcodePyqt4Jiaocheng/js/plugins/__init__.py
zetcode_pyqt4_jiaocheng-2024.3.2.0.dist-info/METADATA
zetcode_pyqt4_jiaocheng-2024.3.2.0.dist-info/WHEEL
zetcode_pyqt4_jiaocheng-2024.3.2.0.dist-info/entry_points.txt
zetcode_pyqt4_jiaocheng-2024.3.2.0.dist-info/top_level.txt
zetcode_pyqt4_jiaocheng-2024.3.2.0.dist-info/RECORD
